microbin/__init__.py
microbin/__version__.py
microbin/json2mb.py
microbin/mb2json.py
microbin/mbstat.py
microbin/reader.py
microbin/type.py
microbin/writer.py
microbin-1.0.1.dist-info/METADATA
microbin-1.0.1.dist-info/WHEEL
microbin-1.0.1.dist-info/licenses/LICENSE
microbin-1.0.1.dist-info/RECORD
