Metadata-Version: 2.1
Name: microbin
Version: 1.0.1
Summary: Compact binary serialization format
Project-URL: Homepage, https://github.com/neko-neko-nayn/python-microbin
Project-URL: Issues, https://github.com/neko-neko-nayn/python-microbin/issues
Author-email: NekoNekoNyan <me@neko-dev.ru>
License: MIT License
License-File: LICENSE
Classifier: License :: OSI Approved :: MIT License
Classifier: Operating System :: OS Independent
Classifier: Programming Language :: Python :: 3
Requires-Python: >=3.8
